<?xml version="1.0" encoding="UTF-8"?>
<objects serializationModel="Studio.02.02.00">
	<object class="AudioFile" id="{0892030b-80b8-4c34-8eb8-fe134f6baee8}">
		<property name="assetPath">
			<value>MehmetKaan's Sounds/AboutUndertale/lazertime.wav</value>
		</property>
		<property name="isStreaming">
			<value>true</value>
		</property>
		<property name="frequencyInKHz">
			<value>44.0999985</value>
		</property>
		<property name="channelCount">
			<value>2</value>
		</property>
		<property name="length">
			<value>24.935056689342403</value>
		</property>
		<relationship name="masterAssetFolder">
			<destination>{e99cf438-2726-4180-ae7c-09d78201d6b5}</destination>
		</relationship>
	</object>
</objects>
